README.md
setup.py
pytezergis/__init__.py
pytezergis/geomathutils.py
pytezergis.egg-info/PKG-INFO
pytezergis.egg-info/SOURCES.txt
pytezergis.egg-info/dependency_links.txt
pytezergis.egg-info/top_level.txt
pytezergis/raster/__init__.py
pytezergis/raster/abstract.py
pytezergis/raster/kml.py
pytezergis/raster/kmz.py
pytezergis/raster/raster.py
pytezergis/raster/shapefile.py
pytezergis/spatial/__init__.py
pytezergis/spatial/bbox.py
pytezergis/spatial/envelope.py
pytezergis/spatial/extent.py
pytezergis/spatial/georeference.py
pytezergis/spatial/latlng.py
pytezergis/spatial/linestring.py
pytezergis/spatial/polygon.py
pytezergis/spatial/wkt.py