Metadata-Version: 1.0
Name: pytezergis
Version: 1.3
Summary: Pacote responsável pela manipulação de dados geospaciais
Home-page: UNKNOWN
Author: Manoel Neco Jr
Author-email: necoengenheiro@gmail.com
License: UNKNOWN
Platform: UNKNOWN
